MANIFEST.in
setup.py
eventtools/__init__.py
eventtools/admin.py
eventtools/adminviews.py
eventtools/forms.py
eventtools/periods.py
eventtools/utils.py
eventtools/conf/__init__.py
eventtools/conf/settings.py
eventtools/locale/de/LC_MESSAGES/django.mo
eventtools/locale/de/LC_MESSAGES/django.po
eventtools/locale/en/LC_MESSAGES/django.mo
eventtools/locale/en/LC_MESSAGES/django.po
eventtools/locale/es/LC_MESSAGES/django.mo
eventtools/locale/es/LC_MESSAGES/django.po
eventtools/locale/es/LC_MESSAGES/django.pot
eventtools/locale/fr/LC_MESSAGES/django.mo
eventtools/locale/fr/LC_MESSAGES/django.po
eventtools/locale/tr_TR/LC_MESSAGES/django.mo
eventtools/locale/tr_TR/LC_MESSAGES/django.po
eventtools/models/__init__.py
eventtools/models/events.py
eventtools/models/eventvariations.py
eventtools/models/occurrencegenerators.py
eventtools/models/occurrences.py
eventtools/models/rules.py
eventtools/models/utils.py
eventtools/templates/annotated_day.html
eventtools/templates/month_calendar.html
eventtools/templates/month_header.html
eventtools/templates/admin/eventtools/list_occurrences.html
eventtools/templates/admin/eventtools/occurrence/change_form.html
eventtools/templates/admin/eventtools/occurrence/change_list.html
eventtools/templatetags/__init__.py
eventtools/templatetags/eventstags.py
eventtools/templatetags/month_calendar.py
eventtools/tests/__init__.py
eventtools/tests/_inject_app.py
eventtools/tests/test_models.py
eventtools/tests/test_periods.py
eventtools/tests/eventtools_testapp/__init__.py
eventtools/tests/eventtools_testapp/models.py
glamkit_eventtools.egg-info/PKG-INFO
glamkit_eventtools.egg-info/SOURCES.txt
glamkit_eventtools.egg-info/dependency_links.txt
glamkit_eventtools.egg-info/not-zip-safe
glamkit_eventtools.egg-info/requires.txt
glamkit_eventtools.egg-info/top_level.txt