Metadata-Version: 1.0
Name: glamkit-eventtools
Version: 0.5.1
Summary: An event management app for Django.
Home-page: http://github.com/glamkit/glamkit-eventtools
Author: Thomas Ashelford
Author-email: thomas@interaction.net.au
License: BSD
Platform: UNKNOWN
Classifier: Development Status :: 4 - Beta
Classifier: Environment :: Web Environment
Classifier: Framework :: Django
Classifier: Intended Audience :: Developers
Classifier: License :: OSI Approved :: BSD License
Classifier: Operating System :: OS Independent
Classifier: Programming Language :: Python
Classifier: Topic :: Utilities
